README.rst
setup.py
broc/__init__.py
broc/cli.py
broc/db.py
broc.egg-info/PKG-INFO
broc.egg-info/SOURCES.txt
broc.egg-info/dependency_links.txt
broc.egg-info/entry_points.txt
broc.egg-info/requires.txt
broc.egg-info/top_level.txt
broc/git-hooks/__init__.py
broc/git-hooks/post_commit_hook.py