Metadata-Version: 1.1
Name: broc
Version: 0.1.2
Summary: Broc: the brownie coder. Code for brownie points
Home-page: UNKNOWN
Author: Charanjit Singh
Author-email: ckhabra@gmail.com
License: MIT
Platform: UNKNOWN
Classifier: Programming Language :: Python
Classifier: Programming Language :: Python :: 2.7
